Metadata-Version: 1.0
Name: sshASA
Version: 2.0
Summary: python3 ssh module for Cisco ASA
Home-page: https://github.com/FedericoOlivieri/networkAutomation/blob/master/python/modules/sshASA/sshASA/__init__.py
Author: Federico Olivieri
Author-email: lvrfrc87@gmail.com
License: MIT
Platform: UNKNOWN
